plot/__init__.py
plot/app.py
lock_plot-0.1.0.dist-info/WHEEL
lock_plot-0.1.0.dist-info/entry_points.txt
lock_plot-0.1.0.dist-info/METADATA
lock_plot-0.1.0.dist-info/RECORD
